feishuconnector/__init__.py
feishuconnector/_version.py
feishuconnector/encoder.py
feishuconnector/manager.py
feishuconnector-0.1.8.dist-info/LICENSE
feishuconnector-0.1.8.dist-info/METADATA
feishuconnector-0.1.8.dist-info/WHEEL
feishuconnector-0.1.8.dist-info/top_level.txt
feishuconnector-0.1.8.dist-info/RECORD
