Metadata-Version: 2.1
Name: feishuconnector
Version: 0.1.8
Summary: connect feishu content franchise
Home-page: http://www.puyuan.tech
Author: Changhao Jiang
Author-email: jch@puyuan.tech
License: MIT License
Platform: all
Classifier: Development Status :: 4 - Beta
Classifier: Operating System :: OS Independent
Classifier: Intended Audience :: Developers
Classifier: License :: OSI Approved :: MIT License
Classifier: Programming Language :: Python
Classifier: Programming Language :: Python :: Implementation
Classifier: Programming Language :: Python :: 3.7
Classifier: Topic :: Software Development :: Libraries
License-File: LICENSE
Requires-Dist: requests (>=2.26.0)
Requires-Dist: numpy (>=1.21.2)
Requires-Dist: pandas (>=1.3.3)
Requires-Dist: requests-toolbelt (>=0.9.1)
Requires-Dist: dataframe-image-cn (>=0.1.1)
